base_cacheable_class/__init__.py
base_cacheable_class/base.py
base_cacheable_class/cache/__init__.py
base_cacheable_class/cache/in_memory/__init__.py
base_cacheable_class/cache/in_memory/cache.py
base_cacheable_class/cache/in_memory/decorator.py
base_cacheable_class/cache/redis/__init__.py
base_cacheable_class/cache/redis/cache.py
base_cacheable_class/cache/redis/decorator.py
base_cacheable_class/interfaces/__init__.py
base_cacheable_class/interfaces/cache.py
base_cacheable_class/interfaces/decorator.py
base_cacheable_class/models/__init__.py
base_cacheable_class/models/cache_item.py
base_cacheable_class-0.1.0.dist-info/WHEEL
base_cacheable_class-0.1.0.dist-info/METADATA
base_cacheable_class-0.1.0.dist-info/RECORD
