Metadata-Version: 2.3
Name: base-cacheable-class
Version: 0.1.0
Summary: A flexible base class for adding caching capabilities to your Python classes
Keywords: cache,caching,decorator,redis,in-memory
Author: Your Name
Author-email: Your Name <your.email@example.com>
License: MIT
Classifier: Development Status :: 4 - Beta
Classifier: Intended Audience :: Developers
Classifier: License :: OSI Approved :: MIT License
Classifier: Programming Language :: Python :: 3
Classifier: Programming Language :: Python :: 3.10
Classifier: Programming Language :: Python :: 3.11
Classifier: Programming Language :: Python :: 3.12
Classifier: Topic :: Software Development :: Libraries :: Python Modules
Requires-Dist: redis>=6.2.0
Requires-Dist: pytest>=7.0.0 ; extra == 'dev'
Requires-Dist: pytest-asyncio>=0.21.0 ; extra == 'dev'
Requires-Dist: pytest-cov>=4.0.0 ; extra == 'dev'
Requires-Dist: ruff>=0.1.0 ; extra == 'dev'
Requires-Dist: mypy>=1.0.0 ; extra == 'dev'
Requires-Dist: black>=23.0.0 ; extra == 'dev'
Requires-Dist: redis>=5.0.0 ; extra == 'redis'
Requires-Python: >=3.10
Project-URL: Documentation, https://github.com/yourusername/base-cacheable-class#readme
Project-URL: Homepage, https://github.com/yourusername/base-cacheable-class
Project-URL: Issues, https://github.com/yourusername/base-cacheable-class/issues
Project-URL: Repository, https://github.com/yourusername/base-cacheable-class
Provides-Extra: dev
Provides-Extra: redis
